dashadmdv_music_player_sync/__init__.py
dashadmdv_music_player_sync/auth_sync.py
dashadmdv_music_player_sync/path_settings.py
dashadmdv_music_player_sync-0.1.0.dist-info/METADATA
dashadmdv_music_player_sync-0.1.0.dist-info/WHEEL
dashadmdv_music_player_sync-0.1.0.dist-info/top_level.txt
dashadmdv_music_player_sync-0.1.0.dist-info/RECORD
