Metadata-Version: 2.1
Name: dashadmdv-music-player-sync
Version: 0.1.0
Summary: Custom sync for my music player
Author: dashadmdv
License: MIT
